{
  "project_info": {
    "project_number": "68152209146",
    "firebase_url": "https://yovideo-da3d2.firebaseio.com",
    "project_id": "yovideo-da3d2",
    "storage_bucket": "yovideo-da3d2.appspot.com"
  },
  "client": [
    {
      "client_info": {
        "mobilesdk_app_id": "1:68152209146:android:25512f129526ead6",
        "android_client_info": {
          "package_name": "com.inspius.canyon.yo_video"
        }
      },
      "oauth_client": [
        {
          "client_id": "68152209146-9fjt21tj61at2ge2jipasb1f98v5jcm0.apps.googleusercontent.com",
          "client_type": 3
        }
      ],
      "api_key": [
        {
          "current_key": "AIzaSyDFxZ1SYaasKECC7FJJgGW4FvChM-eG_2E"
        }
      ],
      "services": {
        "analytics_service": {
          "status": 1
        },
        "appinvite_service": {
          "status": 1,
          "other_platform_oauth_client": []
        },
        "ads_service": {
          "status": 2
        }
      }
    }
  ],
  "configuration_version": "1"
}